{"computer": "klovia", "conjureVersion": "Conjure v2.5.1 (Repository version b988be20f0 (2025-03-24 22:07:42 +0000))",
 "essence": "/cs/home/ed237/Documents/VIPWork/conjure-oxide/tools/performance/tests/nqueens-8/nqueens-8.eprime",
 "essenceParams": [], "runsolverInfo": {},
 "savilerowInfo":
     {"SavileRowClauseOut": "0", "SavileRowTimeOut": "0", "SavileRowTotalTime": "0.35", "SolverNodes": "487",
      "SolverSatisfiable": "1", "SolverSetupTime": "0", "SolverSolutionsFound": "92", "SolverSolveTime": "0.001855",
      "SolverTimeOut": "0", "SolverTotalTime": "0.001855"},
 "savilerowLogs":
     {"exitCode": 0,
      "stdout":
          ["Created output file for domain filtering /cs/home/ed237/Documents/VIPWork/conjure-oxide/tools/performance/data/O2_CN/nqueens-8/model000001.eprime-minion",
           "Created output file /cs/home/ed237/Documents/VIPWork/conjure-oxide/tools/performance/data/O2_CN/nqueens-8/model000001.eprime-minion",
           "Created information file /cs/home/ed237/Documents/VIPWork/conjure-oxide/tools/performance/data/O2_CN/nqueens-8/model000001.eprime-info"]},
 "savilerowOptions": ["-O2"],
 "savilerowVersion": "Savile Row 1.10.0 (Repository Version: 1aded299f (2024-03-10 10:56:22 +0000))",
 "solver": "minion", "solverOptions": [], "status": "OK", "timestamp": "2025-04-29T00:31:34.476981044Z",
 "totalTime": 0.35, "useExistingModels": []}